shadowconf/__init__.py
shadowconf-0.0.1.dist-info/METADATA
shadowconf-0.0.1.dist-info/WHEEL
shadowconf-0.0.1.dist-info/top_level.txt
shadowconf-0.0.1.dist-info/RECORD
